nothingapi/__init__.py
nothingapi/guild.py
nothingapi/user.py
nothingapi-2.0.0.dist-info/METADATA
nothingapi-2.0.0.dist-info/WHEEL
nothingapi-2.0.0.dist-info/licenses/LICENSE
nothingapi-2.0.0.dist-info/RECORD
