Metadata-Version: 2.1
Name: nothingapi
Version: 2.0.0
Summary: The Official Python API Wrapper for the Nothing Currency!
Project-URL: Homepage, https://github.com/MaskdDev/nothingapi
Project-URL: Bug Tracker, https://github.com/MaskdDev/nothingapi/issues
Author-email: MaskdDev <maskddev@gmail.com>
License-File: LICENSE
Classifier: License :: OSI Approved :: MIT License
Classifier: Operating System :: OS Independent
Classifier: Programming Language :: Python :: 3
Requires-Python: >=3.7
Requires-Dist: requests==2.28.1
